{
    "moduleFileExtensions": [
        "ts",
        "tsx",
        "js"
    ],
    "bail": true,
    "moduleDirectories": [
        "node_modules"
    ],
    "moduleNameMapper": {
        "\\.(html|jpg|jpeg|png|gif|eot|otf|webp|svg|ttf|woff|woff2|mp4|webm|wav|mp3|m4a|aac|oga)$": "<rootDir>/__mocks__/fileMock.js",
        "\\.(css|less|scss)$": "<rootDir>/__mocks__/styleMock.js"        
    },
    "transform": {
        "^.+\\.(ts|tsx)$": "<rootDir>/node_modules/ts-jest/preprocessor.js"
    },
    "testPathIgnorePatterns": [
        "/.tmp/",
        "/build/"
    ],
    "coverageDirectory": "coverage_jest_raw",
    "collectCoverage": true,
    "collectCoverageFrom": [
        "**/src/**/*.{ts,tsx}"
    ],
    "coveragePathIgnorePatterns": [
        "/node_modules/",
        "/__tests__/.*\\.(ts|js)$",
        "/build/.*\\.(ts|js)$"
    ],
    "testRegex": "(/__tests__/.*|\\-(test|spec))\\.(ts|tsx|js)$"
}